climap/__init__.py
climap/__version__.py
climap/_client.py
climap/_config.py
climap/_console.py
climap/_exceptions.py
climap/_imap.py
climap/_layout.py
climap/_themes.py
climap/_types.py
climap/main.py
climap-0.1.1.dist-info/LICENSE
climap-0.1.1.dist-info/WHEEL
climap-0.1.1.dist-info/METADATA
climap-0.1.1.dist-info/entry_points.txt
climap-0.1.1.dist-info/RECORD
