Metadata-Version: 2.1
Name: climap
Version: 0.1.1
Summary: A rich command line utility for accessing emails
Author: symonk
Author-email: jackofspaces@gmail.com
Requires-Python: >=3.8,<4.0
Classifier: Programming Language :: Python :: 3
Classifier: Programming Language :: Python :: 3.8
Classifier: Programming Language :: Python :: 3.9
Classifier: Programming Language :: Python :: 3.10
Classifier: Programming Language :: Python :: 3.11
Requires-Dist: rich (==13.3.1)
